systemloader/__init__.py
systemloader/cli.py
systemloader/commands/__init__.py
systemloader/commands/update.py
systemloader/core/__init__.py
systemloader/core/main.py
systemloader/core/app/Dispatcher.py
systemloader/core/app/__init__.py
systemloader/core/app/const.py
systemloader/core/app/connection/CronPrint.py
systemloader/core/app/connection/Postgre.py
systemloader/core/app/connection/__init__.py
systemloader/core/app/module/__init__.py
systemloader/core/app/module/validate_json_header.py
systemloader/core/app/worker/MyCounter.py
systemloader/core/app/worker/__init__.py
systemloader/core/system/Daemon.py
systemloader/core/system/Dispatcher.py
systemloader/core/system/__init__.py
systemloader/core/system/const.py
systemloader/core/system/connection/AIORedisGraph.py
systemloader/core/system/connection/BaseConnection.py
systemloader/core/system/connection/Cron.py
systemloader/core/system/connection/Dadata.py
systemloader/core/system/connection/FirebasePush.py
systemloader/core/system/connection/KeyCloak.py
systemloader/core/system/connection/KeyCloakDecodeToken.py
systemloader/core/system/connection/Mattermost.py
systemloader/core/system/connection/Mongo.py
systemloader/core/system/connection/MsSql.py
systemloader/core/system/connection/Neo4j.py
systemloader/core/system/connection/Oracle.py
systemloader/core/system/connection/Postgre.py
systemloader/core/system/connection/RabbitMQ.py
systemloader/core/system/connection/Redis.py
systemloader/core/system/connection/RedisAsyncio.py
systemloader/core/system/connection/S3.py
systemloader/core/system/connection/S3AioBotoCore.py
systemloader/core/system/connection/Sentry.py
systemloader/core/system/connection/Slack.py
systemloader/core/system/connection/Telegram.py
systemloader/core/system/connection/TelegramSender.py
systemloader/core/system/connection/Web.py
systemloader/core/system/connection/Zulip.py
systemloader/core/system/connection/__init__.py
systemloader/core/system/module/AIOHttpSender.py
systemloader-0.1.5.dist-info/METADATA
systemloader-0.1.5.dist-info/WHEEL
systemloader-0.1.5.dist-info/entry_points.txt
systemloader-0.1.5.dist-info/top_level.txt
systemloader-0.1.5.dist-info/RECORD
