Metadata-Version: 2.4
Name: systemloader
Version: 0.1.5
Summary: Загрузка движка
Author: Alex Yanchenko
Author-email: videoproc@yandex.ru
Project-URL: GitFlic, https://gitflic.ru/project/alexyan/systemloader
Keywords: cli,systemloader
Requires-Python: >=3.12
Requires-Dist: click>=8.0.0
Dynamic: author
Dynamic: author-email
Dynamic: keywords
Dynamic: project-url
Dynamic: requires-dist
Dynamic: requires-python
Dynamic: summary
